people/__init__.py
people/urls.py
people/views.py
people/apps/__init__.py
people/apps/dashboard.py
people/apps/profile.py
people/apps/search.py
people/apps/descriptions/__init__.py
people/apps/descriptions/degrees_app.py
people/apps/descriptions/grouptype_app.py
people/apps/descriptions/positions_app.py
people/apps/descriptions/scientific_areas_app.py
people/apps/groups/__init__.py
people/apps/groups/groups_form.py
people/apps/groups/groups_list.py
people/apps/groups/memberships.py
people/apps/groups/mygroups_form.py
people/apps/groups/mygroups_list.py
people/apps/people/__init__.py
people/apps/people/humanresources_list.py
people/apps/people/humanresourses_form.py
people/apps/people/inline_academic_career.py
people/apps/people/inline_auth_groups.py
people/apps/people/inline_groups.py
people/apps/people/inline_institution_affiliation.py
people/apps/people/people_form.py
people/apps/people/people_list.py
people/fixtures/initial_data.yaml
people/migrations/0001_initial.py
people/migrations/0002_auto_20190805_1713.py
people/migrations/0003_auto_20190806_1516.py
people/migrations/0004_auto_20190806_1713.py
people/migrations/0005_auto_20190823_1342.py
people/migrations/__init__.py
people/models/__init__.py
people/models/group/__init__.py
people/models/group/group.py
people/models/group/group_membership.py
people/models/group/group_membership_queryset.py
people/models/group/group_queryset.py
people/models/group/group_type.py
people/models/group/position.py
people/models/person/__init__.py
people/models/person/academic_career.py
people/models/person/degree.py
people/models/person/institution_affiliation.py
people/models/person/person.py
people/models/person/person_queryset.py
people/models/person/scientific_area.py
people/static/square-image.png
core_people-0.8.dist-info/METADATA
core_people-0.8.dist-info/WHEEL
core_people-0.8.dist-info/top_level.txt
core_people-0.8.dist-info/RECORD
