Metadata-Version: 2.1
Name: core-people
Version: 0.8
Summary: Research CORE ERM - people module
Home-page: https://github.com/research-core/core-people
Author: Ricardo Ribeiro, Hugo Cachitas
Author-email: ricardojvr@gmail.com, hugo.cachitas@research.fchampalimaud.org
License: MIT
Platform: UNKNOWN
Requires-Dist: core-common
